{"sql": "SELECT \n    renewed_dt AS date\nFROM\n    srcdt.account_periods\nWHERE\n    account_renewal_cnt = 1 \nUNION \nSELECT \n    renewed_dt AS date\nFROM\n    srcdt.account_periods\nWHERE\n    account_renewal_cnt > 1 \nUNION \nSELECT \n    expiration_dt AS date\nFROM\n    srcdt.account_periods\nWHERE\n    account_renewal_cnt > 1\n        AND valid_to_dttm = '5999-01-01 00:00:00'\nORDER BY date\n\n", "valid_until": 2044700958.800591, "rows": 4237, "hash": -9206640921426873215, "data": "(datetime.date(2010, 1, 2),)"}